{
  "_store": [
    {
      "_type": "MONTHLY",
      "_name": "ANZ",
      "_date": "2018-01-01T00:00:00.000Z",
      "_b": 0.223,
      "_i": 0.265
    },
    {
      "_type": "MONTHLY",
      "_name": "ANZ",
      "_date": "2018-02-01T00:00:00.000Z",
      "_b": 0.188,
      "_i": 0.293
    },
    {
      "_type": "MONTHLY",
      "_name": "ANZ",
      "_date": "2018-03-01T00:00:00.000Z",
      "_b": 0.282,
      "_i": 0.23
    },
    {
      "_type": "MONTHLY",
      "_name": "ANZ",
      "_date": "2018-04-01T00:00:00.000Z",
      "_b": 0.426,
      "_i": 0.199
    },
    {
      "_type": "MONTHLY",
      "_name": "ANZ",
      "_date": "2018-05-01T00:00:00.000Z",
      "_b": 0.548,
      "_i": 0.198
    },
    {
      "_type": "MONTHLY",
      "_name": "ANZ",
      "_date": "2018-06-01T00:00:00.000Z",
      "_b": 0.504,
      "_i": 0.216
    },
    {
      "_type": "MONTHLY",
      "_name": "ANZ",
      "_date": "2018-07-01T00:00:00.000Z",
      "_b": 0.419,
      "_i": 0.18
    },
    {
      "_type": "YTD",
      "_name": "ANZ",
      "_date": "2018-07-01T00:00:00.000Z",
      "_b": 0.376,
      "_i": 0.225
    },
    {
      "_type": "MONTHLY",
      "_name": "ASEAN",
      "_date": "2018-01-01T00:00:00.000Z",
      "_b": 0.244,
      "_i": 0.119
    },
    {
      "_type": "MONTHLY",
      "_name": "ASEAN",
      "_date": "2018-02-01T00:00:00.000Z",
      "_b": 0.221,
      "_i": 0.183
    },
    {
      "_type": "MONTHLY",
      "_name": "ASEAN",
      "_date": "2018-03-01T00:00:00.000Z",
      "_b": 0.336,
      "_i": 0.199
    },
    {
      "_type": "MONTHLY",
      "_name": "ASEAN",
      "_date": "2018-04-01T00:00:00.000Z",
      "_b": 0.223,
      "_i": 0.295
    },
    {
      "_type": "MONTHLY",
      "_name": "ASEAN",
      "_date": "2018-05-01T00:00:00.000Z",
      "_b": 0.343,
      "_i": 0.284
    },
    {
      "_type": "MONTHLY",
      "_name": "ASEAN",
      "_date": "2018-06-01T00:00:00.000Z",
      "_b": 0.347,
      "_i": 0.276
    },
    {
      "_type": "MONTHLY",
      "_name": "ASEAN",
      "_date": "2018-07-01T00:00:00.000Z",
      "_b": 0.32,
      "_i": 0.251
    },
    {
      "_type": "YTD",
      "_name": "ASEAN",
      "_date": "2018-07-01T00:00:00.000Z",
      "_b": 0.29,
      "_i": 0.23
    },
    {
      "_type": "MONTHLY",
      "_name": "INDIA",
      "_date": "2018-01-01T00:00:00.000Z",
      "_b": 0.034,
      "_i": 0.239
    },
    {
      "_type": "MONTHLY",
      "_name": "INDIA",
      "_date": "2018-02-01T00:00:00.000Z",
      "_b": 0,
      "_i": 0.046
    },
    {
      "_type": "MONTHLY",
      "_name": "INDIA",
      "_date": "2018-03-01T00:00:00.000Z",
      "_b": 0,
      "_i": 0.133
    },
    {
      "_type": "MONTHLY",
      "_name": "INDIA",
      "_date": "2018-04-01T00:00:00.000Z",
      "_b": 0,
      "_i": 0.346
    },
    {
      "_type": "MONTHLY",
      "_name": "INDIA",
      "_date": "2018-05-01T00:00:00.000Z",
      "_b": 0,
      "_i": 0.438
    },
    {
      "_type": "MONTHLY",
      "_name": "INDIA",
      "_date": "2018-06-01T00:00:00.000Z",
      "_b": 0,
      "_i": 0.505
    },
    {
      "_type": "MONTHLY",
      "_name": "INDIA",
      "_date": "2018-07-01T00:00:00.000Z",
      "_b": 0,
      "_i": 0.211
    },
    {
      "_type": "YTD",
      "_name": "INDIA",
      "_date": "2018-07-01T00:00:00.000Z",
      "_b": 0.005,
      "_i": 0.275
    },
    {
      "_type": "MONTHLY",
      "_name": "S.KOREA",
      "_date": "2018-01-01T00:00:00.000Z",
      "_b": 0,
      "_i": 0.074
    },
    {
      "_type": "MONTHLY",
      "_name": "S.KOREA",
      "_date": "2018-02-01T00:00:00.000Z",
      "_b": 0,
      "_i": 0.02
    },
    {
      "_type": "MONTHLY",
      "_name": "S.KOREA",
      "_date": "2018-03-01T00:00:00.000Z",
      "_b": 0,
      "_i": 0.203
    },
    {
      "_type": "MONTHLY",
      "_name": "S.KOREA",
      "_date": "2018-04-01T00:00:00.000Z",
      "_b": 0.157,
      "_i": 0.247
    },
    {
      "_type": "MONTHLY",
      "_name": "S.KOREA",
      "_date": "2018-05-01T00:00:00.000Z",
      "_b": 0.058,
      "_i": 0.228
    },
    {
      "_type": "MONTHLY",
      "_name": "S.KOREA",
      "_date": "2018-06-01T00:00:00.000Z",
      "_b": 0.018,
      "_i": 0.411
    },
    {
      "_type": "MONTHLY",
      "_name": "S.KOREA",
      "_date": "2018-07-01T00:00:00.000Z",
      "_b": 0,
      "_i": 0.383
    },
    {
      "_type": "YTD",
      "_name": "S.KOREA",
      "_date": "2018-07-01T00:00:00.000Z",
      "_b": 0.036,
      "_i": 0.229
    },
    {
      "_type": "MONTHLY",
      "_name": "APAC",
      "_date": "2018-01-01T00:00:00.000Z",
      "_b": 0.189,
      "_i": 0.179
    },
    {
      "_type": "MONTHLY",
      "_name": "APAC",
      "_date": "2018-02-01T00:00:00.000Z",
      "_b": 0.168,
      "_i": 0.206
    },
    {
      "_type": "MONTHLY",
      "_name": "APAC",
      "_date": "2018-03-01T00:00:00.000Z",
      "_b": 0.251,
      "_i": 0.208
    },
    {
      "_type": "MONTHLY",
      "_name": "APAC",
      "_date": "2018-04-01T00:00:00.000Z",
      "_b": 0.279,
      "_i": 0.255
    },
    {
      "_type": "MONTHLY",
      "_name": "APAC",
      "_date": "2018-05-01T00:00:00.000Z",
      "_b": 0.382,
      "_i": 0.248
    },
    {
      "_type": "MONTHLY",
      "_name": "APAC",
      "_date": "2018-06-01T00:00:00.000Z",
      "_b": 0.353,
      "_i": 0.281
    },
    {
      "_type": "MONTHLY",
      "_name": "APAC",
      "_date": "2018-07-01T00:00:00.000Z",
      "_b": 0.303,
      "_i": 0.234
    },
    {
      "_type": "YTD",
      "_name": "APAC",
      "_date": "2018-07-01T00:00:00.000Z",
      "_b": 0.278,
      "_i": 0.231
    },
    {
      "_type": "MONTHLY",
      "_name": "JAPAN",
      "_date": "2018-01-01T00:00:00.000Z",
      "_b": 0.21,
      "_i": 0.129
    },
    {
      "_type": "MONTHLY",
      "_name": "JAPAN",
      "_date": "2018-02-01T00:00:00.000Z",
      "_b": 0.46,
      "_i": 0.246
    },
    {
      "_type": "MONTHLY",
      "_name": "JAPAN",
      "_date": "2018-03-01T00:00:00.000Z",
      "_b": 0.586,
      "_i": 0.292
    },
    {
      "_type": "MONTHLY",
      "_name": "JAPAN",
      "_date": "2018-04-01T00:00:00.000Z",
      "_b": 0.268,
      "_i": 0.19
    },
    {
      "_type": "MONTHLY",
      "_name": "JAPAN",
      "_date": "2018-05-01T00:00:00.000Z",
      "_b": 0.328,
      "_i": 0.259
    },
    {
      "_type": "MONTHLY",
      "_name": "JAPAN",
      "_date": "2018-06-01T00:00:00.000Z",
      "_b": 0.389,
      "_i": 0.22
    },
    {
      "_type": "MONTHLY",
      "_name": "JAPAN",
      "_date": "2018-07-01T00:00:00.000Z",
      "_b": 0.347,
      "_i": 0.221
    },
    {
      "_type": "YTD",
      "_name": "JAPAN",
      "_date": "2018-07-01T00:00:00.000Z",
      "_b": 0.372,
      "_i": 0.225
    },
    {
      "_type": "MONTHLY",
      "_name": "APJ Shared",
      "_date": "2018-01-01T00:00:00.000Z",
      "_b": 0,
      "_i": 0.203
    },
    {
      "_type": "MONTHLY",
      "_name": "APJ Shared",
      "_date": "2018-02-01T00:00:00.000Z",
      "_b": 0.018,
      "_i": 0.33
    },
    {
      "_type": "MONTHLY",
      "_name": "APJ Shared",
      "_date": "2018-03-01T00:00:00.000Z",
      "_b": 0.017,
      "_i": 0.175
    },
    {
      "_type": "MONTHLY",
      "_name": "APJ Shared",
      "_date": "2018-04-01T00:00:00.000Z",
      "_b": 0,
      "_i": 0.125
    },
    {
      "_type": "MONTHLY",
      "_name": "APJ Shared",
      "_date": "2018-05-01T00:00:00.000Z",
      "_b": 0,
      "_i": 0.138
    },
    {
      "_type": "MONTHLY",
      "_name": "APJ Shared",
      "_date": "2018-06-01T00:00:00.000Z",
      "_b": 0,
      "_i": 0.157
    },
    {
      "_type": "MONTHLY",
      "_name": "APJ Shared",
      "_date": "2018-07-01T00:00:00.000Z",
      "_b": 0,
      "_i": 0.062
    },
    {
      "_type": "YTD",
      "_name": "APJ Shared",
      "_date": "2018-07-01T00:00:00.000Z",
      "_b": 0.005,
      "_i": 0.174
    },
    {
      "_type": "MONTHLY",
      "_name": "APJ",
      "_date": "2018-01-01T00:00:00.000Z",
      "_b": 0.182,
      "_i": 0.169
    },
    {
      "_type": "MONTHLY",
      "_name": "APJ",
      "_date": "2018-02-01T00:00:00.000Z",
      "_b": 0.225,
      "_i": 0.222
    },
    {
      "_type": "MONTHLY",
      "_name": "APJ",
      "_date": "2018-03-01T00:00:00.000Z",
      "_b": 0.32,
      "_i": 0.227
    },
    {
      "_type": "MONTHLY",
      "_name": "APJ",
      "_date": "2018-04-01T00:00:00.000Z",
      "_b": 0.262,
      "_i": 0.232
    },
    {
      "_type": "MONTHLY",
      "_name": "APJ",
      "_date": "2018-05-01T00:00:00.000Z",
      "_b": 0.348,
      "_i": 0.245
    },
    {
      "_type": "MONTHLY",
      "_name": "APJ",
      "_date": "2018-06-01T00:00:00.000Z",
      "_b": 0.347,
      "_i": 0.258
    },
    {
      "_type": "MONTHLY",
      "_name": "APJ",
      "_date": "2018-07-01T00:00:00.000Z",
      "_b": 0.3,
      "_i": 0.223
    },
    {
      "_type": "YTD",
      "_name": "APJ",
      "_date": "2018-07-01T00:00:00.000Z",
      "_b": 0.286,
      "_i": 0.226
    },
    {
      "_type": "YTD",
      "_name": "ANZ",
      "_date": "2018-01-31T00:00:00.000Z",
      "_b": 0.223,
      "_i": 0.265
    },
    {
      "_type": "YTD",
      "_name": "APJ Shared",
      "_date": "2018-01-31T00:00:00.000Z",
      "_b": 0,
      "_i": 0.203
    },
    {
      "_type": "YTD",
      "_name": "ASEAN",
      "_date": "2018-01-31T00:00:00.000Z",
      "_b": 0.244,
      "_i": 0.119
    },
    {
      "_type": "YTD",
      "_name": "INDIA",
      "_date": "2018-01-31T00:00:00.000Z",
      "_b": 0.034,
      "_i": 0.239
    },
    {
      "_type": "YTD",
      "_name": "JAPAN",
      "_date": "2018-01-31T00:00:00.000Z",
      "_b": 0.21,
      "_i": 0.129
    },
    {
      "_type": "YTD",
      "_name": "S.KOREA",
      "_date": "2018-01-31T00:00:00.000Z",
      "_b": 0,
      "_i": 0.074
    },
    {
      "_type": "YTD",
      "_name": "APJ",
      "_date": "2018-01-31T00:00:00.000Z",
      "_b": 0.182,
      "_i": 0.169
    },
    {
      "_type": "YTD",
      "_name": "APAC",
      "_date": "2018-01-31T00:00:00.000Z",
      "_b": 0.189,
      "_i": 0.179
    },
    {
      "_type": "YTD",
      "_name": "ANZ",
      "_date": "2018-02-28T00:00:00.000Z",
      "_b": 0.205,
      "_i": 0.28
    },
    {
      "_type": "YTD",
      "_name": "APJ Shared",
      "_date": "2018-02-28T00:00:00.000Z",
      "_b": 0.08,
      "_i": 0.263
    },
    {
      "_type": "YTD",
      "_name": "ASEAN",
      "_date": "2018-02-28T00:00:00.000Z",
      "_b": 0.233,
      "_i": 0.148
    },
    {
      "_type": "YTD",
      "_name": "INDIA",
      "_date": "2018-02-28T00:00:00.000Z",
      "_b": 0.17,
      "_i": 0.141
    },
    {
      "_type": "YTD",
      "_name": "JAPAN",
      "_date": "2018-02-28T00:00:00.000Z",
      "_b": 0.336,
      "_i": 0.188
    },
    {
      "_type": "YTD",
      "_name": "S.KOREA",
      "_date": "2018-02-28T00:00:00.000Z",
      "_b": 0,
      "_i": 0.051
    },
    {
      "_type": "YTD",
      "_name": "APJ",
      "_date": "2018-02-28T00:00:00.000Z",
      "_b": 0.203,
      "_i": 0.195
    },
    {
      "_type": "YTD",
      "_name": "APAC",
      "_date": "2018-02-28T00:00:00.000Z",
      "_b": 0.179,
      "_i": 0.191
    },
    {
      "_type": "YTD",
      "_name": "ANZ",
      "_date": "2018-03-31T00:00:00.000Z",
      "_b": 0.223,
      "_i": 0.262
    },
    {
      "_type": "YTD",
      "_name": "APJ Shared",
      "_date": "2018-03-31T00:00:00.000Z",
      "_b": 0.11,
      "_i": 0.234
    },
    {
      "_type": "YTD",
      "_name": "ASEAN",
      "_date": "2018-03-31T00:00:00.000Z",
      "_b": 0.269,
      "_i": 0.165
    },
    {
      "_type": "YTD",
      "_name": "INDIA",
      "_date": "2018-03-31T00:00:00.000Z",
      "_b": 0.11,
      "_i": 0.138
    },
    {
      "_type": "YTD",
      "_name": "JAPAN",
      "_date": "2018-03-31T00:00:00.000Z",
      "_b": 0.432,
      "_i": 0.228
    },
    {
      "_type": "YTD",
      "_name": "S.KOREA",
      "_date": "2018-03-31T00:00:00.000Z",
      "_b": 0,
      "_i": 0.104
    },
    {
      "_type": "YTD",
      "_name": "APJ",
      "_date": "2018-03-31T00:00:00.000Z",
      "_b": 0.245,
      "_i": 0.206
    },
    {
      "_type": "YTD",
      "_name": "APAC",
      "_date": "2018-03-31T00:00:00.000Z",
      "_b": 0.204,
      "_i": 0.197
    },
    {
      "_type": "YTD",
      "_name": "ANZ",
      "_date": "2018-04-30T00:00:00.000Z",
      "_b": 0.279,
      "_i": 0.247
    },
    {
      "_type": "YTD",
      "_name": "APJ Shared",
      "_date": "2018-04-30T00:00:00.000Z",
      "_b": 0.008,
      "_i": 0.207
    },
    {
      "_type": "YTD",
      "_name": "ASEAN",
      "_date": "2018-04-30T00:00:00.000Z",
      "_b": 0.257,
      "_i": 0.201
    },
    {
      "_type": "YTD",
      "_name": "INDIA",
      "_date": "2018-04-30T00:00:00.000Z",
      "_b": 0.008,
      "_i": 0.191
    },
    {
      "_type": "YTD",
      "_name": "JAPAN",
      "_date": "2018-04-30T00:00:00.000Z",
      "_b": 0.387,
      "_i": 0.217
    },
    {
      "_type": "YTD",
      "_name": "S.KOREA",
      "_date": "2018-04-30T00:00:00.000Z",
      "_b": 0.044,
      "_i": 0.144
    },
    {
      "_type": "YTD",
      "_name": "APJ",
      "_date": "2018-04-30T00:00:00.000Z",
      "_b": 0.249,
      "_i": 0.213
    },
    {
      "_type": "YTD",
      "_name": "APAC",
      "_date": "2018-04-30T00:00:00.000Z",
      "_b": 0.224,
      "_i": 0.212
    },
    {
      "_type": "YTD",
      "_name": "ANZ",
      "_date": "2018-05-31T00:00:00.000Z",
      "_b": 0.34,
      "_i": 0.236
    },
    {
      "_type": "YTD",
      "_name": "APJ Shared",
      "_date": "2018-05-31T00:00:00.000Z",
      "_b": 0.07,
      "_i": 0.192
    },
    {
      "_type": "YTD",
      "_name": "ASEAN",
      "_date": "2018-05-31T00:00:00.000Z",
      "_b": 0.274,
      "_i": 0.218
    },
    {
      "_type": "YTD",
      "_name": "INDIA",
      "_date": "2018-05-31T00:00:00.000Z",
      "_b": 0.07,
      "_i": 0.24
    },
    {
      "_type": "YTD",
      "_name": "JAPAN",
      "_date": "2018-05-31T00:00:00.000Z",
      "_b": 0.373,
      "_i": 0.227
    },
    {
      "_type": "YTD",
      "_name": "S.KOREA",
      "_date": "2018-05-31T00:00:00.000Z",
      "_b": 0.047,
      "_i": 0.161
    },
    {
      "_type": "YTD",
      "_name": "APJ",
      "_date": "2018-05-31T00:00:00.000Z",
      "_b": 0.271,
      "_i": 0.22
    },
    {
      "_type": "YTD",
      "_name": "APAC",
      "_date": "2018-05-31T00:00:00.000Z",
      "_b": 0.257,
      "_i": 0.22
    },
    {
      "_type": "YTD",
      "_name": "ANZ",
      "_date": "2018-06-30T00:00:00.000Z",
      "_b": 0.365,
      "_i": 0.232
    },
    {
      "_type": "YTD",
      "_name": "APJ Shared",
      "_date": "2018-06-30T00:00:00.000Z",
      "_b": 0.006,
      "_i": 0.187
    },
    {
      "_type": "YTD",
      "_name": "ASEAN",
      "_date": "2018-06-30T00:00:00.000Z",
      "_b": 0.286,
      "_i": 0.227
    },
    {
      "_type": "YTD",
      "_name": "INDIA",
      "_date": "2018-06-30T00:00:00.000Z",
      "_b": 0.005,
      "_i": 0.278
    },
    {
      "_type": "YTD",
      "_name": "JAPAN",
      "_date": "2018-06-30T00:00:00.000Z",
      "_b": 0.376,
      "_i": 0.226
    },
    {
      "_type": "YTD",
      "_name": "S.KOREA",
      "_date": "2018-06-30T00:00:00.000Z",
      "_b": 0.042,
      "_i": 0.2016
    },
    {
      "_type": "YTD",
      "_name": "APJ",
      "_date": "2018-06-30T00:00:00.000Z",
      "_b": 0.283,
      "_i": 0.227
    },
    {
      "_type": "YTD",
      "_name": "APAC",
      "_date": "2018-06-30T00:00:00.000Z",
      "_b": 0.272,
      "_i": 0.23
    }
  ],
  "_types": [
    "Billable",
    "Investment",
    "Total"
  ],
  "_monthly": [],
  "_ytd": [],
  "_top": [
    {
      "name": "JAPAN",
      "total": 0.878,
      "date": "2018-03-01T00:00:00.000Z",
      "type": "MONTHLY"
    },
    {
      "name": "ANZ",
      "total": 0.746,
      "date": "2018-05-01T00:00:00.000Z",
      "type": "MONTHLY"
    },
    {
      "name": "ANZ",
      "total": 0.72,
      "date": "2018-06-01T00:00:00.000Z",
      "type": "MONTHLY"
    },
    {
      "name": "JAPAN",
      "total": 0.706,
      "date": "2018-02-01T00:00:00.000Z",
      "type": "MONTHLY"
    },
    {
      "name": "JAPAN",
      "total": 0.66,
      "date": "2018-03-31T00:00:00.000Z",
      "type": "YTD"
    },
    {
      "name": "ASEAN",
      "total": 0.627,
      "date": "2018-05-01T00:00:00.000Z",
      "type": "MONTHLY"
    },
    {
      "name": "ANZ",
      "total": 0.625,
      "date": "2018-04-01T00:00:00.000Z",
      "type": "MONTHLY"
    },
    {
      "name": "ASEAN",
      "total": 0.623,
      "date": "2018-06-01T00:00:00.000Z",
      "type": "MONTHLY"
    },
    {
      "name": "JAPAN",
      "total": 0.609,
      "date": "2018-06-01T00:00:00.000Z",
      "type": "MONTHLY"
    },
    {
      "name": "JAPAN",
      "total": 0.604,
      "date": "2018-04-30T00:00:00.000Z",
      "type": "YTD"
    }
  ],
  "_bottom": [
    {
      "name": "S.KOREA",
      "total": 0.02,
      "date": "2018-02-01T00:00:00.000Z",
      "type": "MONTHLY"
    },
    {
      "name": "INDIA",
      "total": 0.046,
      "date": "2018-02-01T00:00:00.000Z",
      "type": "MONTHLY"
    },
    {
      "name": "S.KOREA",
      "total": 0.051,
      "date": "2018-02-28T00:00:00.000Z",
      "type": "YTD"
    },
    {
      "name": "S.KOREA",
      "total": 0.074,
      "date": "2018-01-01T00:00:00.000Z",
      "type": "MONTHLY"
    },
    {
      "name": "S.KOREA",
      "total": 0.074,
      "date": "2018-01-31T00:00:00.000Z",
      "type": "YTD"
    },
    {
      "name": "S.KOREA",
      "total": 0.104,
      "date": "2018-03-31T00:00:00.000Z",
      "type": "YTD"
    },
    {
      "name": "INDIA",
      "total": 0.133,
      "date": "2018-03-01T00:00:00.000Z",
      "type": "MONTHLY"
    },
    {
      "name": "S.KOREA",
      "total": 0.188,
      "date": "2018-04-30T00:00:00.000Z",
      "type": "YTD"
    },
    {
      "name": "INDIA",
      "total": 0.199,
      "date": "2018-04-30T00:00:00.000Z",
      "type": "YTD"
    },
    {
      "name": "S.KOREA",
      "total": 0.203,
      "date": "2018-03-01T00:00:00.000Z",
      "type": "MONTHLY"
    }
  ],
  "_names": [
    "ANZ",
    "ASEAN",
    "INDIA",
    "S.KOREA",
    "APAC",
    "JAPAN",
    "APJ Shared",
    "APJ"
  ],
  "_date": "2018-08-29T16:00:00.000Z",
  "_reader": {
    "practices": [
      {
        "name": "ANZ",
        "lookup": "ANZ"
      },
      {
        "name": "ASEAN",
        "lookup": "ASEAN"
      },
      {
        "name": "INDIA",
        "lookup": "INDIA"
      },
      {
        "name": "S.KOREA",
        "lookup": "S. KOREA"
      },
      {
        "name": "APAC",
        "lookup": "APAC"
      },
      {
        "name": "JAPAN",
        "lookup": "JAPAN"
      },
      {
        "name": "APJ Shared",
        "lookup": "APJ Shared"
      },
      {
        "name": "APJ",
        "lookup": "APJ"
      }
    ],
    "records": [],
    "ws": null
  }
}